src/ALU.v
module alu (
    input [15:0] a,
    input [15:0] b,
    input [1:0] sel,
    output reg [15:0] s
);

    always @(*) begin
        case(sel)
            2'b00: s = a + b;
            2'b01: s = a & b;
            2'b10: s = ~a;
            2'b11: s = a;
        endcase
    end

endmodule

tb/tb_ALU.v
`timescale 1ns/1ps


module tb_ALU;

    //input reg
    reg [15:0] a;
    reg [15:0] b;
    reg [1:0] sel;
    //output wire
    wire [15:0] s;

    alu test_alu (
       .a(a),
       .b(b),
       .sel(sel),
       .s(s)
    );

    initial begin
        $dumpfile("sim/alu.vcd");
        $dumpvars(0, tb_ALU);

        //add
        a = 16'd1; b = 16'd3; sel = 2'd0;
        #10;  //wait
        if (s !== 32'd4)
            $display("FAIL ADD: expected 4, got %0d", s);
        else
            $display("PASS ADD");

        //overflow edgecase
        a = 16'hFFFF; b = 16'd1; sel = 2'd0;
        #10;
        if (s !== 16'd0)
            $display("FAIL ADD overflow: expected 0, got %0d", s);
        else
            $display("PASS ADD overflow");

        //adding zeros
        a = 16'd0; b = 16'd0; sel = 2'd0;
        #10;
        if (s !== 16'd0)
            $display("FAIL ADD zero: expected 0, got %0h", s);
        else
            $display("PASS ADD zero");

        //and
        a = 16'hFEFE; b = 16'hAABB; sel = 2'd1;
        #10;
        if (s !== 16'hAABA)
            $display("FAIL AND: expected AABA, got %0h", s);
        else
            $display("PASS AND");

        //and zero
        a = 16'hABCD; b = 16'h0000; sel = 2'd1;
        #10;
        if (s !== 16'h0000)
            $display("FAIL AND zero: expected 0, got %0h", s);
        else
            $display("PASS AND zero");

        //not
        a = 16'hAABB; b = 16'hEEEE; sel = 2'd2;
        #10;
        if (s !== 16'h5544)
            $display("FAIL NOT: expected 5544, got %0h", s);
        else
            $display("PASS NOT");

        //not 0
        a = 16'h0000; b = 16'hEEEE; sel = 2'd2;
        #10;
        if (s !== 16'hFFFF)
            $display("FAIL NOT zero: expected FFFF, got %0h", s);
        else
            $display("PASS NOT zero");

        //pass
        a = 16'h4242; b = 16'hEEEE; sel = 2'd3;
        #10;
        if (s !== 16'h4242)
            $display("FAIL, PASS: expected 4242, got %0h", s);
        else
            $display("PASS, PASS");

    end

endmodule

sim/alu.vcd
$date
	Mon May 25 23:19:30 2026
$end
$version
	Icarus Verilog
$end
$timescale
	1ps
$end
$scope module tb_ALU $end
$var wire 16 ! s [15:0] $end
$var reg 16 " a [15:0] $end
$var reg 16 # b [15:0] $end
$var reg 2 $ sel [1:0] $end
$scope module test_alu $end
$var wire 16 % a [15:0] $end
$var wire 16 & b [15:0] $end
$var wire 2 ' sel [1:0] $end
$var reg 16 ( s [15:0] $end
$upscope $end
$upscope $end
$enddefinitions $end
$comment Show the parameter values. $end
$dumpall
$end
#0
$dumpvars
b100 (
b0 '
b11 &
b1 %
b0 $
b11 #
b1 "
b100 !
$end
#10000
b0 !
b0 (
b1 #
b1 &
b1111111111111111 "
b1111111111111111 %
#20000
b0 #
b0 &
b0 "
b0 %
#30000
b1010101010111010 !
b1010101010111010 (
b1 $
b1 '
b1010101010111011 #
b1010101010111011 &
b1111111011111110 "
b1111111011111110 %
#40000
b0 !
b0 (
b0 #
b0 &
b1010101111001101 "
b1010101111001101 %
#50000
b101010101000100 !
b101010101000100 (
b10 $
b10 '
b1110111011101110 #
b1110111011101110 &
b1010101010111011 "
b1010101010111011 %
#60000
b1111111111111111 !
b1111111111111111 (
b0 "
b0 %
#70000
b100001001000010 !
b100001001000010 (
b11 $
b11 '
b100001001000010 "
b100001001000010 %
