src/CONTROL.v

//all caps is used for easier wiring of datapath
module control (
    input R,
    input BEN,
    input [15:0] IR,
    input CLK,
    input RESET,
    // Register LD signals
    output reg LD_MAR,
    output reg LD_MDR,
    output reg LD_IR,
    output reg LD_PC,
    output reg LD_REG,
    output reg LD_BEN,
    output reg LD_CC,
    // MUX select bits
    output reg MARMUX,
    output reg ADDR1MUX,
    output reg [1:0] ADDR2MUX,
    output reg [1:0] PCMUX,
    output reg [1:0] SR1MUX,
    output reg [1:0] DRMUX,
    // Tri-state buffers gate for bus
    output reg GateMARMUX,
    output reg GateMDR,
    output reg GateALU,
    output reg GatePC,
    // Memory
    output reg MIO_EN,
    output reg RW,
    // ALU select bits
    output reg [1:0] ALUK,
    output [5:0] current_state //only used for microsequencer testing
);

    reg [5:0] STATE;

    assign current_state = STATE;

    // Microsequencer
    reg IRD;
    reg [2:0] COND;
    reg [5:0] J;

    always @(posedge CLK) begin
        if(RESET)
            STATE <= 6'd18;
        else if(IRD)
            STATE <= {2'b00, IR[15:12]};
        else begin
            STATE <= {
                J[5], J[4], J[3],
                J[2] | (BEN & (COND == 3'd2)),
                J[1] | (R   & (COND == 3'd1)),
                J[0] | (IR[11] & (COND == 3'd3))
            };
        end
    end

    // Microsequencer Outputs (J, COND, IRD)
    always @(*) begin
        // Default/Unsed States
        IRD = 1'b0;
        COND = 3'b000;
        J = 6'b010010;

        case(STATE)
            6'd0:  begin IRD = 1'b0; COND = 3'b010; J = 6'b010010; end
            6'd1:  begin IRD = 1'b0; COND = 3'b000; J = 6'b010010; end
            6'd2:  begin IRD = 1'b0; COND = 3'b000; J = 6'b011001; end
            6'd3:  begin IRD = 1'b0; COND = 3'b000; J = 6'b010111; end
            6'd4:  begin IRD = 1'b0; COND = 3'b011; J = 6'b010100; end
            6'd5:  begin IRD = 1'b0; COND = 3'b000; J = 6'b010010; end
            6'd6:  begin IRD = 1'b0; COND = 3'b000; J = 6'b011001; end
            6'd7:  begin IRD = 1'b0; COND = 3'b000; J = 6'b010111; end
            6'd9:  begin IRD = 1'b0; COND = 3'b000; J = 6'b010010; end
            6'd10: begin IRD = 1'b0; COND = 3'b000; J = 6'b011000; end
            6'd11: begin IRD = 1'b0; COND = 3'b000; J = 6'b011101; end
            6'd12: begin IRD = 1'b0; COND = 3'b000; J = 6'b010010; end
            6'd14: begin IRD = 1'b0; COND = 3'b000; J = 6'b010010; end
            6'd15: begin IRD = 1'b0; COND = 3'b000; J = 6'b011100; end
            6'd16: begin IRD = 1'b0; COND = 3'b001; J = 6'b010000; end
            6'd18: begin IRD = 1'b0; COND = 3'b101; J = 6'b100001; end
            6'd20: begin IRD = 1'b0; COND = 3'b000; J = 6'b010010; end
            6'd21: begin IRD = 1'b0; COND = 3'b000; J = 6'b010010; end
            6'd22: begin IRD = 1'b0; COND = 3'b000; J = 6'b010010; end
            6'd23: begin IRD = 1'b0; COND = 3'b000; J = 6'b010000; end
            6'd24: begin IRD = 1'b0; COND = 3'b001; J = 6'b011000; end
            6'd25: begin IRD = 1'b0; COND = 3'b001; J = 6'b011001; end
            6'd26: begin IRD = 1'b0; COND = 3'b000; J = 6'b011001; end
            6'd27: begin IRD = 1'b0; COND = 3'b000; J = 6'b010010; end
            6'd28: begin IRD = 1'b0; COND = 3'b001; J = 6'b011100; end
            6'd29: begin IRD = 1'b0; COND = 3'b001; J = 6'b011101; end
            6'd30: begin IRD = 1'b0; COND = 3'b000; J = 6'b010010; end
            6'd31: begin IRD = 1'b0; COND = 3'b000; J = 6'b010111; end
            6'd32: begin IRD = 1'b1;                               end
            6'd33: begin IRD = 1'b0; COND = 3'b001; J = 6'b100001; end
            6'd35: begin IRD = 1'b0; COND = 3'b000; J = 6'b100000; end
            default: begin 
                IRD = 1'b0; 
                COND = 3'b000; 
                J = 6'b010010; 
            end
        endcase
    end

    // FSM Inputs (Datapath control signals)
    always @(*) begin

        LD_MAR=1'b0; LD_MDR=1'b0; LD_IR=1'b0; LD_PC=1'b0; LD_REG=1'b0; LD_BEN=1'b0; LD_CC=1'b0;
        GateMARMUX=1'b0; GateMDR=1'b0; GateALU=1'b0; GatePC=1'b0;
        MARMUX=1'b0; ADDR1MUX=1'b0; ADDR2MUX=2'b00;
        PCMUX=2'b00; SR1MUX=2'b00; DRMUX=2'b00; ALUK=2'b00;
        MIO_EN=1'b0; RW=1'b0;

        case(STATE)

            6'd0:  begin 
                //No Changes
            end

            6'd1:  begin 
                LD_REG=1'b1; LD_CC=1'b1;
                GateALU=1'b1;
                SR1MUX=2'b01; DRMUX=2'b00; ALUK=2'b00;
            end

            6'd2:  begin 
                LD_MAR=1'b1;
                GateMARMUX=1'b1;
                MARMUX=1'b1; ADDR1MUX=1'b0; ADDR2MUX=2'b10;
            end

            6'd3:  begin 
                LD_MAR=1'b1;
                GateMARMUX=1'b1;
                MARMUX=1'b1; ADDR1MUX=1'b0; ADDR2MUX=2'b10;
            end

            6'd4:  begin 
                LD_REG=1'b1;
                GatePC=1'b1;
                DRMUX=2'b01;
            end

            6'd5:  begin 
                LD_REG=1'b1; LD_CC=1'b1;
                GateALU=1'b1;
                SR1MUX=2'b01; DRMUX=2'b00; ALUK=2'b01;
            end

            6'd6:  begin 
                LD_MAR=1'b1;
                GateMARMUX=1'b1;
                MARMUX=1'b1; ADDR1MUX=1'b1; ADDR2MUX=2'b01;
                SR1MUX=2'b01;
            end

            6'd7:  begin 
                LD_MAR=1'b1;
                GateMARMUX=1'b1;
                MARMUX=1'b1; ADDR1MUX=1'b1; ADDR2MUX=2'b01;
                SR1MUX=2'b01;
            end

            6'd9:  begin 
                LD_REG=1'b1; LD_CC=1'b1;
                GateALU=1'b1;
                SR1MUX=2'b01; DRMUX=2'b00; ALUK=2'b10;
            end

            6'd10:  begin 
                LD_MAR=1'b1;
                GateMARMUX=1'b1;
                MARMUX=1'b1; ADDR1MUX=1'b0; ADDR2MUX=2'b10;
            end

            6'd11:  begin 
                LD_MAR=1'b1;
                GateMARMUX=1'b1;
                MARMUX=1'b1; ADDR1MUX=1'b0; ADDR2MUX=2'b10;
            end

            6'd12:  begin 
                LD_PC=1'b1;
                GateALU=1'b1;
                PCMUX=2'b01; SR1MUX=2'b01; ALUK=2'b11;
            end

            6'd14:  begin 
                LD_REG=1'b1; LD_CC=1'b1;
                GateMARMUX=1'b1;
                MARMUX=1'b1; ADDR1MUX=1'b0; ADDR2MUX=2'b10;
                DRMUX=2'b00;
            end

            6'd15:  begin 
                LD_MAR=1'b1;
                GateMARMUX=1'b1;
                MARMUX=1'b0;
            end

            6'd16:  begin 
                MIO_EN=1'b1; RW=1'b1;
            end

            6'd18:  begin 
                LD_MAR=1'b1; LD_PC=1'b1;
                GatePC=1'b1;
                PCMUX=2'b00;
            end

            6'd20:  begin 
                LD_PC=1'b1;
                GateALU=1'b1;
                PCMUX=2'b01; SR1MUX=2'b01; ALUK=2'b11;
            end

            6'd21:  begin 
                LD_PC=1'b1;
                ADDR1MUX=1'b0; ADDR2MUX=2'b11;
                PCMUX=2'b10;
            end

            6'd22:  begin 
                LD_PC=1'b1;
                ADDR1MUX=1'b0; ADDR2MUX=2'b10;
                PCMUX=2'b10;
            end

            6'd23:  begin 
                LD_MDR=1'b1;
                GateALU=1'b1;
                SR1MUX=2'b00; ALUK=2'b11;
            end

            6'd24:  begin 
                LD_MDR=1'b1;
                MIO_EN=1'b1; RW=1'b0;
            end

            6'd25:  begin 
                LD_MDR=1'b1;
                MIO_EN=1'b1; RW=1'b0;
            end

            6'd26:  begin 
                LD_MAR=1'b1;
                GateMDR=1'b1;
            end

            6'd27:  begin 
                LD_REG=1'b1; LD_CC=1'b1;
                GateMDR=1'b1;
                DRMUX=2'b00;
            end

            6'd28:  begin 
                LD_MDR=1'b1; LD_REG=1'b1;
                GatePC=1'b1;
                DRMUX=2'b01;
                MIO_EN=1'b1; RW=1'b0;
            end

            6'd29:  begin 
                LD_MDR=1'b1;
                MIO_EN=1'b1; RW=1'b0;
            end

            6'd30:  begin 
                LD_PC=1'b1;
                GateMDR=1'b1;
                PCMUX=2'b01;
            end

            6'd31:  begin 
                LD_MAR=1'b1;
                GateMDR=1'b1;
            end

            6'd32:  begin 
                LD_BEN=1'b1;
            end

            6'd33:  begin 
                LD_MDR=1'b1;
                MIO_EN=1'b1; RW=1'b0;
            end

            6'd35:  begin 
                LD_IR=1'b1;
                GateMDR=1'b1;
            end

            default: begin
                LD_MAR=1'b0; LD_MDR=1'b0; LD_IR=1'b0; LD_PC=1'b0; LD_REG=1'b0; LD_BEN=1'b0; LD_CC=1'b0;
                GateMARMUX=1'b0; GateMDR=1'b0; GateALU=1'b0; GatePC=1'b0;
                MARMUX=1'b0; ADDR1MUX=1'b0; ADDR2MUX=2'b00;
                PCMUX=2'b00; SR1MUX=2'b00; DRMUX=2'b00; ALUK=2'b00;
                MIO_EN=1'b0; RW=1'b0;
            end

        endcase
    end

endmodule

tb/tb_CONTROL.v
`timescale 1ns/1ps


//Only use for microsequencer testing. Outputs are just based on case statements
module tb_CONTROL;

    reg R;
    reg BEN;
    reg [15:0] IR;
    reg CLK;
    reg RESET;

    wire [5:0] current_state;

    wire LD_MAR;
    wire LD_MDR;
    wire LD_IR;
    wire LD_PC;
    wire LD_REG;
    wire LD_BEN;
    wire LD_CC;
    wire MARMUX;
    wire ADDR1MUX;
    wire [1:0] ADDR2MUX;
    wire [1:0] PCMUX;
    wire [1:0] SR1MUX;
    wire [1:0] DRMUX;
    wire GateMARMUX;
    wire GateMDR;
    wire GateALU;
    wire GatePC;
    wire MIO_EN;
    wire RW;
    wire [1:0] ALUK;

    control test_control (
        .R(R),
        .BEN(BEN),
        .IR(IR),
        .CLK(CLK),
        .RESET(RESET),
        .LD_MAR(LD_MAR),
        .LD_MDR(LD_MDR),
        .LD_IR(LD_IR),
        .LD_PC(LD_PC),
        .LD_REG(LD_REG),
        .LD_BEN(LD_BEN),
        .LD_CC(LD_CC),
        .MARMUX(MARMUX),
        .ADDR1MUX(ADDR1MUX),
        .ADDR2MUX(ADDR2MUX),
        .PCMUX(PCMUX),
        .SR1MUX(SR1MUX),
        .DRMUX(DRMUX),
        .GateMARMUX(GateMARMUX),
        .GateMDR(GateMDR),
        .GateALU(GateALU),
        .GatePC(GatePC),
        .MIO_EN(MIO_EN),
        .RW(RW),
        .ALUK(ALUK),
        .current_state(current_state)
    );

    initial begin
        CLK = 1'b0;

        $dumpfile("sim/control.vcd");
        $dumpvars(0, tb_CONTROL);

        //RESET to state 18
        CLK = 1'b0;
        RESET = 1'b1;
        #10;
        CLK = 1'b1;
        #10;
        CLK = 1'b0;
        #10;
        RESET = 1'b0;
        $display("State after reset: %0d", current_state);

        // ==================== ADD ====================

        R = 1'b0; BEN = 1'b0;
        IR = 16'h1000;
        #10;

        if(current_state != 6'd18)
            $display("FAIL FETCH1: expected state 18, got %0d", current_state);
        else
            $display("PASS FETCH1");

        CLK = 1'b0;
        #10;
        CLK = 1'b1;
        #10;

        if(current_state != 6'd33)
            $display("FAIL FETCH2: expected state 33, got %0d", current_state);
        else
            $display("PASS FETCH2");

        CLK = 1'b0;
        #10;
        CLK = 1'b1;
        #10;

        if(current_state != 6'd33)
            $display("FAIL FETCH2R: expected state 33, got %0d", current_state);
        else
            $display("PASS FETCH2R");

        R = 1'b1;

        CLK = 1'b0;
        #10;
        CLK = 1'b1;
        #10;

        if(current_state != 6'd35)
            $display("FAIL FETCH3: expected state 35, got %0d", current_state);
        else
            $display("PASS FETCH3");

        CLK = 1'b0;
        #10;
        CLK = 1'b1;
        #10;

        if(current_state != 6'd32)
            $display("FAIL DECODE1: expected state 32, got %0d", current_state);
        else
            $display("PASS DECODE1");

        CLK = 1'b0;
        #10;
        CLK = 1'b1;
        #10;

        if(current_state != 6'd1)
            $display("FAIL ADD: expected state 1, got %0d", current_state);
        else
            $display("PASS ADD");

        CLK = 1'b0;
        #10;
        CLK = 1'b1;
        #10;

        // ==================== AND ====================

        BEN = 1'b0;
        IR = 16'h5000;

        if(current_state != 6'd18)
            $display("FAIL FETCH4: expected state 18, got %0d", current_state);
        else
            $display("PASS FETCH4");

        CLK = 1'b0;
        #10;
        CLK = 1'b1;
        #10;

        if(current_state != 6'd33)
            $display("FAIL FETCH5: expected state 33, got %0d", current_state);
        else
            $display("PASS FETCH5");

        CLK = 1'b0;
        #10;
        CLK = 1'b1;
        #10;

        if(current_state != 6'd35)
            $display("FAIL FETCH6: expected state 35, got %0d", current_state);
        else
            $display("PASS FETCH6");
        
        CLK = 1'b0;
        #10;
        CLK = 1'b1;
        #10;

        if(current_state != 6'd32)
            $display("FAIL DECODE2: expected state 32, got %0d", current_state);
        else
            $display("PASS DECODE2");

        CLK = 1'b0;
        #10;
        CLK = 1'b1;
        #10;

        if(current_state != 6'd5)
            $display("FAIL AND: expected state 5, got %0d", current_state);
        else
            $display("PASS AND");

        CLK = 1'b0;
        #10;
        CLK = 1'b1;
        #10;

        // ==================== NOT ====================

        BEN = 1'b0;
        IR = 16'h903F;

        if(current_state != 6'd18)
            $display("FAIL FETCH7: expected state 18, got %0d", current_state);
        else
            $display("PASS FETCH7");

        CLK = 1'b0;
        #10;
        CLK = 1'b1;
        #10;

        if(current_state != 6'd33)
            $display("FAIL FETCH8: expected state 33, got %0d", current_state);
        else
            $display("PASS FETCH8");

        CLK = 1'b0;
        #10;
        CLK = 1'b1;
        #10;

        if(current_state != 6'd35)
            $display("FAIL FETCH9: expected state 35, got %0d", current_state);
        else
            $display("PASS FETCH9");
        
        CLK = 1'b0;
        #10;
        CLK = 1'b1;
        #10;

        if(current_state != 6'd32)
            $display("FAIL DECODE3: expected state 32, got %0d", current_state);
        else
            $display("PASS DECODE3");

        CLK = 1'b0;
        #10;
        CLK = 1'b1;
        #10;

        if(current_state != 6'd9)
            $display("FAIL NOT: expected state 9, got %0d", current_state);
        else
            $display("PASS NOT");

        CLK = 1'b0;
        #10;
        CLK = 1'b1;
        #10;

        // ==================== TRAP ====================

        BEN = 1'b0;
        IR = 16'hF000;

        if(current_state != 6'd18)
            $display("FAIL FETCH10: expected state 18, got %0d", current_state);
        else
            $display("PASS FETCH10");

        CLK = 1'b0;
        #10;
        CLK = 1'b1;
        #10;

        if(current_state != 6'd33)
            $display("FAIL FETCH11: expected state 33, got %0d", current_state);
        else
            $display("PASS FETCH11");

        CLK = 1'b0;
        #10;
        CLK = 1'b1;
        #10;

        if(current_state != 6'd35)
            $display("FAIL FETCH12: expected state 35, got %0d", current_state);
        else
            $display("PASS FETCH12");
        
        CLK = 1'b0;
        #10;
        CLK = 1'b1;
        #10;

        if(current_state != 6'd32)
            $display("FAIL DECODE4: expected state 32, got %0d", current_state);
        else
            $display("PASS DECODE4");

        CLK = 1'b0;
        #10;
        CLK = 1'b1;
        #10;

        if(current_state != 6'd15)
            $display("FAIL TRAP1: expected state 15, got %0d", current_state);
        else
            $display("PASS TRAP1");

        CLK = 1'b0;
        #10;
        CLK = 1'b1;
        #10;

        R = 1'b0;

        if(current_state != 6'd28)
            $display("FAIL TRAP2: expected state 28, got %0d", current_state);
        else
            $display("PASS TRAP2");

        CLK = 1'b0;
        #10;
        CLK = 1'b1;
        #10;

        R = 1'b1;

        if(current_state != 6'd28)
            $display("FAIL TRAP2R: expected state 28, got %0d", current_state);
        else
            $display("PASS TRAP2R");

        CLK = 1'b0;
        #10;
        CLK = 1'b1;
        #10;

        if(current_state != 6'd30)
            $display("FAIL TRAP3: expected state 30, got %0d", current_state);
        else
            $display("PASS TRAP3");

        CLK = 1'b0;
        #10;
        CLK = 1'b1;
        #10;

        // ==================== LEA ====================

        BEN = 1'b0;
        IR = 16'hE000;

        if(current_state != 6'd18)
            $display("FAIL FETCH13: expected state 18, got %0d", current_state);
        else
            $display("PASS FETCH13");

        CLK = 1'b0;
        #10;
        CLK = 1'b1;
        #10;

        if(current_state != 6'd33)
            $display("FAIL FETCH14: expected state 33, got %0d", current_state);
        else
            $display("PASS FETCH14");

        CLK = 1'b0;
        #10;
        CLK = 1'b1;
        #10;

        if(current_state != 6'd35)
            $display("FAIL FETCH15: expected state 35, got %0d", current_state);
        else
            $display("PASS FETCH15");
        
        CLK = 1'b0;
        #10;
        CLK = 1'b1;
        #10;

        if(current_state != 6'd32)
            $display("FAIL DECODE5: expected state 32, got %0d", current_state);
        else
            $display("PASS DECODE5");

        CLK = 1'b0;
        #10;
        CLK = 1'b1;
        #10;

        if(current_state != 6'd14)
            $display("FAIL LEA: expected state 14, got %0d", current_state);
        else
            $display("PASS LEA");

        CLK = 1'b0;
        #10;
        CLK = 1'b1;
        #10;

        // ==================== LD ====================

        BEN = 1'b0;
        IR = 16'h5000;

        if(current_state != 6'd18)
            $display("FAIL FETCH13: expected state 18, got %0d", current_state);
        else
            $display("PASS FETCH13");

        CLK = 1'b0;
        #10;
        CLK = 1'b1;
        #10;

        if(current_state != 6'd33)
            $display("FAIL FETCH14: expected state 33, got %0d", current_state);
        else
            $display("PASS FETCH14");

        CLK = 1'b0;
        #10;
        CLK = 1'b1;
        #10;

        if(current_state != 6'd35)
            $display("FAIL FETCH15: expected state 35, got %0d", current_state);
        else
            $display("PASS FETCH15");
        
        CLK = 1'b0;
        #10;
        CLK = 1'b1;
        #10;

        if(current_state != 6'd32)
            $display("FAIL DECODE5: expected state 32, got %0d", current_state);
        else
            $display("PASS DECODE5");

        CLK = 1'b0;
        #10;
        CLK = 1'b1;
        #10;

        if(current_state != 6'd14)
            $display("FAIL LEA: expected state 14, got %0d", current_state);
        else
            $display("PASS LEA");

        CLK = 1'b0;
        #10;
        CLK = 1'b1;
        #10;


    
        $finish;
    end

endmodule

sim/control.vcd
$date
	Fri May 29 20:53:31 2026
$end
$version
	Icarus Verilog
$end
$timescale
	1ps
$end
$scope module tb_CONTROL $end
$var wire 6 ! current_state [5:0] $end
$var wire 2 " SR1MUX [1:0] $end
$var wire 1 # RW $end
$var wire 2 $ PCMUX [1:0] $end
$var wire 1 % MIO_EN $end
$var wire 1 & MARMUX $end
$var wire 1 ' LD_REG $end
$var wire 1 ( LD_PC $end
$var wire 1 ) LD_MDR $end
$var wire 1 * LD_MAR $end
$var wire 1 + LD_IR $end
$var wire 1 , LD_CC $end
$var wire 1 - LD_BEN $end
$var wire 1 . GatePC $end
$var wire 1 / GateMDR $end
$var wire 1 0 GateMARMUX $end
$var wire 1 1 GateALU $end
$var wire 2 2 DRMUX [1:0] $end
$var wire 2 3 ALUK [1:0] $end
$var wire 2 4 ADDR2MUX [1:0] $end
$var wire 1 5 ADDR1MUX $end
$var reg 1 6 BEN $end
$var reg 1 7 CLK $end
$var reg 16 8 IR [15:0] $end
$var reg 1 9 R $end
$var reg 1 : RESET $end
$scope module test_control $end
$var wire 1 6 BEN $end
$var wire 1 7 CLK $end
$var wire 16 ; IR [15:0] $end
$var wire 1 9 R $end
$var wire 1 : RESET $end
$var wire 6 < current_state [5:0] $end
$var reg 1 5 ADDR1MUX $end
$var reg 2 = ADDR2MUX [1:0] $end
$var reg 2 > ALUK [1:0] $end
$var reg 3 ? COND [2:0] $end
$var reg 2 @ DRMUX [1:0] $end
$var reg 1 1 GateALU $end
$var reg 1 0 GateMARMUX $end
$var reg 1 / GateMDR $end
$var reg 1 . GatePC $end
$var reg 1 A IRD $end
$var reg 6 B J [5:0] $end
$var reg 1 - LD_BEN $end
$var reg 1 , LD_CC $end
$var reg 1 + LD_IR $end
$var reg 1 * LD_MAR $end
$var reg 1 ) LD_MDR $end
$var reg 1 ( LD_PC $end
$var reg 1 ' LD_REG $end
$var reg 1 & MARMUX $end
$var reg 1 % MIO_EN $end
$var reg 2 C PCMUX [1:0] $end
$var reg 1 # RW $end
$var reg 2 D SR1MUX [1:0] $end
$var reg 6 E STATE [5:0] $end
$upscope $end
$upscope $end
$enddefinitions $end
$comment Show the parameter values. $end
$dumpall
$end
#0
$dumpvars
bx E
bx D
bx C
bx B
xA
bx @
bx ?
bx >
bx =
bx <
bx ;
1:
x9
bx 8
07
x6
x5
bx 4
bx 3
bx 2
x1
x0
x/
x.
x-
x,
x+
x*
x)
x(
x'
x&
x%
bx $
x#
bx "
bx !
$end
#10000
0#
0%
b0 3
b0 >
b0 2
b0 @
b0 "
b0 D
b0 $
b0 C
b0 4
b0 =
05
0&
1.
01
0/
00
0,
0-
0'
1(
0+
0)
1*
b100001 B
b101 ?
0A
b10010 !
b10010 <
b10010 E
17
#20000
07
#30000
b1000000000000 8
b1000000000000 ;
06
09
0:
#50000
b100001 B
b1 ?
1%
1)
0.
0(
0*
b100001 !
b100001 <
b100001 E
17
#60000
07
#70000
17
#80000
07
19
#90000
1/
1+
0%
0)
b100000 B
b0 ?
b100011 !
b100011 <
b100011 E
17
#100000
07
#110000
1A
b10010 B
1-
0/
0+
b100000 !
b100000 <
b100000 E
17
#120000
07
#130000
b1 "
b1 D
11
1,
1'
0-
0A
b1 !
b1 <
b1 E
17
#140000
07
#150000
b100001 B
b101 ?
1.
1(
1*
b0 "
b0 D
01
0,
0'
b10010 !
b10010 <
b10010 E
17
#160000
07
b101000000000000 8
b101000000000000 ;
#170000
1%
1)
0.
0(
0*
b100001 B
b1 ?
b100001 !
b100001 <
b100001 E
17
#180000
07
#190000
b100000 B
b0 ?
1/
1+
0%
0)
b100011 !
b100011 <
b100011 E
17
#200000
07
#210000
1-
0/
0+
1A
b10010 B
b100000 !
b100000 <
b100000 E
17
#220000
07
#230000
0A
b1 3
b1 >
b1 "
b1 D
11
1,
1'
0-
b101 !
b101 <
b101 E
17
#240000
07
#250000
1.
1(
1*
b0 3
b0 >
b0 "
b0 D
01
0,
0'
b100001 B
b101 ?
b10010 !
b10010 <
b10010 E
17
#260000
07
b1001000000111111 8
b1001000000111111 ;
#270000
b100001 B
b1 ?
1%
1)
0.
0(
0*
b100001 !
b100001 <
b100001 E
17
#280000
07
#290000
1/
1+
0%
0)
b100000 B
b0 ?
b100011 !
b100011 <
b100011 E
17
#300000
07
#310000
1A
b10010 B
1-
0/
0+
b100000 !
b100000 <
b100000 E
17
#320000
07
#330000
b10 3
b10 >
b1 "
b1 D
11
1,
1'
0-
0A
b1001 !
b1001 <
b1001 E
17
#340000
07
#350000
b100001 B
b101 ?
1.
1(
1*
b0 3
b0 >
b0 "
b0 D
01
0,
0'
b10010 !
b10010 <
b10010 E
17
#360000
07
b1111000000000000 8
b1111000000000000 ;
#370000
1%
1)
0.
0(
0*
b100001 B
b1 ?
b100001 !
b100001 <
b100001 E
17
#380000
07
#390000
b100000 B
b0 ?
1/
1+
0%
0)
b100011 !
b100011 <
b100011 E
17
#400000
07
#410000
1-
0/
0+
1A
b10010 B
b100000 !
b100000 <
b100000 E
17
#420000
07
#430000
b11100 B
0A
10
1*
0-
b1111 !
b1111 <
b1111 E
17
#440000
07
#450000
1%
b1 2
b1 @
1.
1'
1)
00
0*
b1 ?
b11100 B
b11100 !
b11100 <
b11100 E
17
#460000
07
09
#470000
17
#480000
07
19
#490000
b10010 B
b0 ?
b1 $
b1 C
1/
1(
0%
b0 2
b0 @
0.
0'
0)
b11110 !
b11110 <
b11110 E
17
#500000
07
#510000
1.
1*
b0 $
b0 C
0/
1(
b100001 B
b101 ?
b10010 !
b10010 <
b10010 E
17
#520000
07
b1110000000000000 8
b1110000000000000 ;
#530000
b100001 B
b1 ?
1%
1)
0.
0(
0*
b100001 !
b100001 <
b100001 E
17
#540000
07
#550000
1/
1+
0%
0)
b100000 B
b0 ?
b100011 !
b100011 <
b100011 E
17
#560000
07
#570000
1A
b10010 B
1-
0/
0+
b100000 !
b100000 <
b100000 E
17
#580000
07
#590000
b10 4
b10 =
1&
10
1,
1'
0-
0A
b1110 !
b1110 <
b1110 E
17
#600000
07
#610000
b100001 B
b101 ?
1.
1(
1*
b0 4
b0 =
0&
00
0,
0'
b10010 !
b10010 <
b10010 E
17
#620000
07
b101000000000000 8
b101000000000000 ;
#630000
1%
1)
0.
0(
0*
b100001 B
b1 ?
b100001 !
b100001 <
b100001 E
17
#640000
07
#650000
b100000 B
b0 ?
1/
1+
0%
0)
b100011 !
b100011 <
b100011 E
17
#660000
07
#670000
1-
0/
0+
1A
b10010 B
b100000 !
b100000 <
b100000 E
17
#680000
07
#690000
0A
b1 3
b1 >
b1 "
b1 D
11
1,
1'
0-
b101 !
b101 <
b101 E
17
#700000
07
#710000
1.
1(
1*
b0 3
b0 >
b0 "
b0 D
01
0,
0'
b100001 B
b101 ?
b10010 !
b10010 <
b10010 E
17
