src/SEXT.v
module sext #(parameter WIDTH = 5) (
    input [WIDTH-1:0] data_in,
    output [15:0] data_out
);

    assign data_out = { {(16 - WIDTH){data_in[WIDTH-1]} }, data_in};

endmodule

tb/tb_SEXT.v
`timescale 1ns/1ps

module tb_SEXT;

    //possible data_ins
    reg [4:0] imm5;
    reg [5:0] offset6;
    reg [8:0] PCoffset9;
    reg [10:0] PCoffset11;

    wire [15:0] out5, out6, out9, out11;

    sext #(5) test_imm5 (.data_in(imm5), .data_out(out5));
    sext #(6) test_offset6 (.data_in(offset6), .data_out(out6));
    sext #(9) test_PCoffset9 (.data_in(PCoffset9), .data_out(out9));
    sext #(11) test_PCoffset11 (.data_in(PCoffset11), .data_out(out11));

    initial begin
        $dumpfile("sim/sext.vcd");
        $dumpvars(0, tb_SEXT);

        //imm5
        imm5 = 5'd3;
        #10;
        if(out5 != 16'd3)
            $display("FAIL IMM5 POS: expected 3, got %0d", out5);
        else   
            $display("PASS IMM5 POS");

        imm5 = 5'b11110;
        #10;
        if(out5 != 16'hFFFE)
            $display("FAIL IMM5 NEG: expected -2, got %0d", out5);
        else   
            $display("PASS IMM5 NEG");

        imm5 = 5'd0;
        #10;
        if(out5 != 16'd0)
            $display("FAIL IMM5 ZERO: expected 0, got %0d", out5);
        else   
            $display("PASS IMM5 ZERO");

        //offset6
        offset6 = 6'd3;
        #10;
        if(out6 != 16'd3)
            $display("FAIL OFFSET6 POS: expected 3, got %0d", out5);
        else   
            $display("PASS OFFSET6 POS");

        offset6 = 6'b111110;
        #10;
        if(out6 != 16'hFFFE)
            $display("FAIL OFFSET6 NEG: expected -2, got %0d", out5);
        else   
            $display("PASS OFFSET6 NEG");

        offset6 = 6'd0;
        #10;
        if(out6 != 16'd0)
            $display("FAIL OFFSET6 ZERO: expected 0, got %0d", out5);
        else   
            $display("PASS OFFSET6 ZERO");

        //offset9
        PCoffset9 = 9'd3;
        #10;
        if(out9 != 16'd3)
            $display("FAIL PCOFFSET9 POS: expected 3, got %0d", out5);
        else   
            $display("PASS PCOFFSET9 POS");

        PCoffset9 = 9'b111111110;
        #10;
        if(out9 != 16'hFFFE)
            $display("FAIL PCOFFSET9 NEG: expected -2, got %0d", out5);
        else   
            $display("PASS PCOFFSET9 NEG");

        PCoffset9 = 9'd0;
        #10;
        if(out9 != 16'd0)
            $display("FAIL PCOFFSET9 ZERO: expected 0, got %0d", out5);
        else   
            $display("PASS PCOFFSET9 ZERO");

        //offset11
        PCoffset11 = 11'd3;
        #10;
        if(out11 != 16'd3)
            $display("FAIL PCOFFSET11 POS: expected 3, got %0d", out5);
        else   
            $display("PASS PCOFFSET11 POS");

        PCoffset11 = 11'b11111111110;
        #10;
        if(out11 != 16'hFFFE)
            $display("FAIL PCOFFSET11 NEG: expected -2, got %0d", out5);
        else   
            $display("PASS PCOFFSET11 NEG");

        PCoffset11 = 11'd0;
        #10;
        if(out11 != 16'd0)
            $display("FAIL PCOFFSET11 ZERO: expected 0, got %0d", out5);
        else   
            $display("PASS PCOFFSET11 ZERO");

        $finish;
    end

endmodule

sim/sext.vcd
$date
	Tue May 26 02:18:45 2026
$end
$version
	Icarus Verilog
$end
$timescale
	1ps
$end
$scope module tb_SEXT $end
$var wire 16 ! out9 [15:0] $end
$var wire 16 " out6 [15:0] $end
$var wire 16 # out5 [15:0] $end
$var wire 16 $ out11 [15:0] $end
$var reg 11 % PCoffset11 [10:0] $end
$var reg 9 & PCoffset9 [8:0] $end
$var reg 5 ' imm5 [4:0] $end
$var reg 6 ( offset6 [5:0] $end
$scope module test_PCoffset11 $end
$var wire 11 ) data_in [10:0] $end
$var wire 16 * data_out [15:0] $end
$var parameter 32 + WIDTH $end
$upscope $end
$scope module test_PCoffset9 $end
$var wire 9 , data_in [8:0] $end
$var wire 16 - data_out [15:0] $end
$var parameter 32 . WIDTH $end
$upscope $end
$scope module test_imm5 $end
$var wire 5 / data_in [4:0] $end
$var wire 16 0 data_out [15:0] $end
$var parameter 32 1 WIDTH $end
$upscope $end
$scope module test_offset6 $end
$var wire 6 2 data_in [5:0] $end
$var wire 16 3 data_out [15:0] $end
$var parameter 32 4 WIDTH $end
$upscope $end
$upscope $end
$enddefinitions $end
$comment Show the parameter values. $end
$dumpall
b110 4
b101 1
b1001 .
b1011 +
$end
#0
$dumpvars
bx 3
bx 2
b11 0
b11 /
bx -
bx ,
bx *
bx )
bx (
b11 '
bx &
bx %
bx $
b11 #
bx "
bx !
$end
#10000
b1111111111111110 #
b1111111111111110 0
b11110 '
b11110 /
#20000
b0 #
b0 0
b0 '
b0 /
#30000
b11 "
b11 3
b11 (
b11 2
#40000
b1111111111111110 "
b1111111111111110 3
b111110 (
b111110 2
#50000
b0 "
b0 3
b0 (
b0 2
#60000
b11 !
b11 -
b11 &
b11 ,
#70000
b1111111111111110 !
b1111111111111110 -
b111111110 &
b111111110 ,
#80000
b0 !
b0 -
b0 &
b0 ,
#90000
b11 $
b11 *
b11 %
b11 )
#100000
b1111111111111110 $
b1111111111111110 *
b11111111110 %
b11111111110 )
#110000
b0 $
b0 *
b0 %
b0 )
