src/SRAM.v
module sram (
    input clk,
    input cs,   //MIO.EN
    input rw,   // R'/W
    input [15:0] addr,
    input [15:0] data_in,
    output reg ready, //ready signal
    output reg [15:0] data_out
); // 64k x 16 RAM
    reg [1:0] counter;
    //smaller memory for testing
    reg [15:0] mem [65536:0];

    //counter for ready signal is not needed but good practice
    always @(posedge clk) begin
        if(cs) begin
            if(ready) begin
                //wait till cs is done so counter doesn't keep going
            end
            else if(counter == 2'b10) begin
                counter <= 2'b00;
                ready <= 1'b1;
            end
            else begin
                counter <= counter + 1;
                ready <= 1'b0;
            end
        end
        else begin
            counter <= 2'b0;
            ready <= 1'b0;
        end
    end

    always @(posedge clk) begin
        if(cs) begin
            if(ready && rw) begin //write
                mem[addr] <= data_in;
            end
        end
    end

    always @(*) begin //read (combinational)
        if(cs && ~rw)
            data_out = mem[addr];
        else
            data_out = 16'h0000;
    end
endmodule

tb/tb_SRAM.v
`timescale 1ns/1ps

module tb_SRAM;

    reg clk;
    reg cs;
    reg rw;
    reg [15:0] addr;
    reg [15:0] data_in;

    wire ready;
    wire [15:0] data_out;

    sram test_sram (
        .clk(clk),
        .cs(cs),
        .rw(rw),
        .addr(addr),
        .data_in(data_in),
        .ready(ready),
        .data_out(data_out)
    );

    always #5 clk = ~clk;

    /* 
        Order for Write then Read

        1. Assert cs, set addr, data_in, rw=1 (write)
        2. Wait for ready
        3. Deassert cs
        5. wait a bit
        4. Assert cs again, same addr, rw=0 (read)
        5. Wait for ready
        6. Sample data_out and check

        This is because we wait for ready to do anything, so for a write, or a read to finish

    */

    initial begin
        clk = 1'b0;

        $dumpfile("sim/sram.vcd");
        $dumpvars(1, tb_SRAM);

        cs = 1'b0;
        repeat(2) @(posedge clk);

        //normal write then read to memory
        cs = 1'b1; addr = 16'd5; data_in = 16'd42; rw = 1'b1;

        @(posedge ready) cs = 1'b0;

        repeat(2) @(posedge clk); //wait two cycles to reassert cs

        cs = 1'b1; addr = 16'd5; rw = 1'b0;            

        @(posedge ready);
        #10
        if (data_out != 16'd42)
            $display("FAIL WR: expected 42, got %0d", data_out);
        else
            $display("PASS WR");

        cs = 1'b0;
        repeat(2) @(posedge clk);


        //wrong wr
        cs = 1'b1; addr = 16'd15; data_in = 16'd42; rw = 1'b0;

        @(posedge ready) cs = 1'b0;

        repeat(2) @(posedge clk);

        cs = 1'b1; addr = 16'd15; rw = 1'b0;            

        @(posedge ready);
        #10
        if (data_out != 16'd0)
            $display("FAIL WWR: expected 0, got %0d", data_out);
        else
            $display("PASS WWR");

        cs = 1'b0;
        repeat(2) @(posedge clk);

        //retain value
        #50

        cs = 1'b1; addr = 16'd5; rw = 1'b0;            

        @(posedge ready);
        #10
        if (data_out != 16'd42)
            $display("FAIL RETAIN: expected 42, got %0d", data_out);
        else
            $display("PASS RETAIN");


        $finish;
    end

endmodule

sim/sram.vcd
$date
	Wed May 27 00:38:06 2026
$end
$version
	Icarus Verilog
$end
$timescale
	1ps
$end
$scope module tb_SRAM $end
$var wire 1 ! ready $end
$var wire 16 " data_out [15:0] $end
$var reg 16 # addr [15:0] $end
$var reg 1 $ clk $end
$var reg 1 % cs $end
$var reg 16 & data_in [15:0] $end
$var reg 1 ' rw $end
$upscope $end
$enddefinitions $end
$comment Show the parameter values. $end
$dumpall
$end
#0
$dumpvars
x'
bx &
0%
0$
bx #
b0 "
x!
$end
#5000
0!
1$
#10000
0$
#15000
1'
b101010 &
b101 #
1%
1$
#20000
0$
#25000
1$
#30000
0$
#35000
1$
#40000
0$
#45000
0%
1!
1$
#50000
0$
#55000
0!
1$
#60000
0$
#65000
bx "
0'
1%
1$
#70000
0$
#75000
1$
#80000
0$
#85000
1$
#90000
0$
#95000
1!
1$
#100000
0$
#105000
0!
b0 "
1$
0%
#110000
0$
#115000
bx "
b1111 #
1%
1$
#120000
0$
#125000
1$
#130000
0$
#135000
1$
#140000
0$
#145000
b0 "
0%
1!
1$
#150000
0$
#155000
0!
1$
#160000
0$
#165000
bx "
1%
1$
#170000
0$
#175000
1$
#180000
0$
#185000
1$
#190000
0$
#195000
1!
1$
#200000
0$
#205000
0!
b0 "
1$
0%
#210000
0$
#215000
1$
#220000
0$
#225000
1$
#230000
0$
#235000
1$
#240000
0$
#245000
1$
#250000
0$
#255000
1$
#260000
0$
#265000
bx "
1$
b101 #
1%
#270000
0$
#275000
1$
#280000
0$
#285000
1!
1$
